setup.py
happybase_monkey/__init__.py
happybase_monkey/monkey.py
happybase_monkey.egg-info/PKG-INFO
happybase_monkey.egg-info/SOURCES.txt
happybase_monkey.egg-info/dependency_links.txt
happybase_monkey.egg-info/requires.txt
happybase_monkey.egg-info/top_level.txt