Metadata-Version: 1.0
Name: happybase-monkey
Version: 1.0.1
Summary: <向 hbase put 数据时，自动建立索引表并向索引表中插入数据>
Home-page: UNKNOWN
Author: applepie
Author-email: 1961356350@qq.com
License: UNKNOWN
Platform: UNKNOWN
